finflo/__init__.py
finflo/admin.py
finflo/api.py
finflo/apps.py
finflo/base_enum.py
finflo/compatability.py
finflo/exception.py
finflo/middleware.py
finflo/models.py
finflo/serializer.py
finflo/signals.py
finflo/tests.py
finflo/transition.py
finflo/urls.py
finflo/validators.py
finflo/migrations/0001_initial.py
finflo/migrations/0002_remigrate.py
finflo/migrations/__init__.py
finflo-2.0.44.dist-info/LICENSE
finflo-2.0.44.dist-info/METADATA
finflo-2.0.44.dist-info/WHEEL
finflo-2.0.44.dist-info/top_level.txt
finflo-2.0.44.dist-info/RECORD
