Metadata-Version: 2.1
Name: finflo
Version: 2.0.44
Author: Anand Raj
Author-email: anandrajb@venzotechnologies.com
License: UNKNOWN
Classifier: Development Status :: 5 - Production/Stable
Classifier: Intended Audience :: Education
Classifier: Operating System :: Microsoft :: Windows :: Windows 10
Classifier: Programming Language :: Python :: 3
Requires-Python: >=3.8
License-File: LICENSE
Requires-Dist: django
Requires-Dist: djangorestframework
